readeckbot/__init__.py
readeckbot/__main__.py
readeckbot/bot.py
readeckbot/config.py
readeckbot/helpers.py
readeckbot/log.py
readeckbot/md_to_dom.py
readeckbot/readeck_client.py
readeckbot/requests.py
readeckbot/telegraph/__init__.py
readeckbot/telegraph/md_to_dom.py
readeckbot-0.1.2.dist-info/entry_points.txt
readeckbot-0.1.2.dist-info/WHEEL
readeckbot-0.1.2.dist-info/METADATA
readeckbot-0.1.2.dist-info/RECORD
