Metadata-Version: 2.4
Name: readeckbot
Version: 0.1.2
Summary: A Telegram bot that interfaces with a self-hosted Readeck instance to manage bookmarks.
Author-email: Martín Gaitán <gaitan@gmail.com>
Requires-Python: >=3.12
Requires-Dist: python-telegram-bot
Requires-Dist: httpx
Requires-Dist: rich
Requires-Dist: python-dotenv
Requires-Dist: telegramify-markdown
Requires-Dist: your-telegraph
Requires-Dist: mistletoe
Requires-Dist: llm>=0.23 ; extra == "llm"
Requires-Dist: llm-gemini>=0.17 ; extra == "llm"
Project-URL: Home, https://github.com/mgaitan/readeckbot
Provides-Extra: llm
